rubi_sdk/init.py
rubi_sdk/types.py
rubi_sdk/client/__init__.py
rubi_sdk/client/card_resolver.py
rubi_sdk/client/client.py
rubi_sdk/server/__init__.py
rubi_sdk/server/server.py
rubi_sdk/server/task_manager.py
rubi_sdk/server/utils.py
rubi_sdk/utils/in_memory_cache.py
rubi_sdk/utils/push_notification_auth.py
rubi_sdk-0.1.2.dist-info/METADATA
rubi_sdk-0.1.2.dist-info/WHEEL
rubi_sdk-0.1.2.dist-info/RECORD
