Metadata-Version: 2.4
Name: rubi_sdk
Version: 0.1.2
Summary: A2A Core SDK - A framework for building AI agents and applications
Requires-Python: >=3.12
Requires-Dist: asyncclick>=8.1.8
Requires-Dist: asyncio>=3.4.3
Requires-Dist: click>=8.1.8
Requires-Dist: httpx-sse>=0.4.0
Requires-Dist: httpx>=0.28.1
Requires-Dist: jwcrypto>=1.5.6
Requires-Dist: pydantic>=2.10.6
Requires-Dist: pyjwt>=2.10.1
Requires-Dist: sse-starlette>=2.2.1
Requires-Dist: starlette>=0.46.1
Requires-Dist: streamlit>=1.44.0
Requires-Dist: uvicorn>=0.34.0
